pywavefront/__init__.py
pywavefront/cache.py
pywavefront/exceptions.py
pywavefront/material.py
pywavefront/mesh.py
pywavefront/obj.py
pywavefront/parser.py
pywavefront/texture.py
pywavefront/visualization.py
pywavefront/wavefront.py
PyWavefront-1.3.1.dist-info/LICENSE
PyWavefront-1.3.1.dist-info/METADATA
PyWavefront-1.3.1.dist-info/WHEEL
PyWavefront-1.3.1.dist-info/top_level.txt
PyWavefront-1.3.1.dist-info/RECORD
