Metadata-Version: 2.1
Name: PyWavefront
Version: 1.3.1
Summary: Python library for importing Wavefront .obj files
Home-page: https://github.com/pywavefront/PyWavefront
Author: Kurt Yoder
Author-email: kyoder@gmail.com
Maintainer: Einar Forselv
Maintainer-email: eforselv@gmail.com
License: BSD
Platform: UNKNOWN
Classifier: Environment :: Plugins
Classifier: Intended Audience :: Developers
Classifier: License :: OSI Approved :: BSD License
Classifier: Operating System :: MacOS :: MacOS X
Classifier: Operating System :: Microsoft :: Windows
Classifier: Operating System :: POSIX :: Linux
Classifier: Natural Language :: English
Classifier: Programming Language :: Python
Classifier: Programming Language :: Python :: 3
Classifier: Programming Language :: Python :: 3.4
Classifier: Programming Language :: Python :: 3.5
Classifier: Programming Language :: Python :: 3.6
Classifier: Programming Language :: Python :: 3.7
Classifier: Topic :: Multimedia :: Graphics :: 3D Rendering
Classifier: Topic :: Software Development :: Libraries :: Python Modules
Requires-Python: >=3.4
Provides-Extra: visualization
Requires-Dist: pyglet ; extra == 'visualization'
